corefinder/__init__.py
corefinder/core_finder.py
corefinder/core_stats.py
corefinder/core_track.py
corefinder3d-0.5.3.dist-info/METADATA
corefinder3d-0.5.3.dist-info/WHEEL
corefinder3d-0.5.3.dist-info/top_level.txt
corefinder3d-0.5.3.dist-info/RECORD
