Metadata-Version: 2.4
Name: corefinder3d
Version: 0.5.3
Summary: A package for finding cores in 3D simulation data.
Author-email: Shibo Yuan <shibo_yuan@outlook.com>
License-Expression: MIT
Classifier: Development Status :: 3 - Alpha
Classifier: Intended Audience :: Developers
Classifier: Programming Language :: Python :: 3
Classifier: Programming Language :: Python :: 3.9
Classifier: Programming Language :: Python :: 3.10
Classifier: Programming Language :: Python :: 3.11
Classifier: Programming Language :: Python :: 3.12
Classifier: Operating System :: OS Independent
Requires-Python: >=3.9
Requires-Dist: numpy>=2.0.0
Requires-Dist: scikit-image>=0.24.0
Requires-Dist: connected-components-3d>=3.18.0
Requires-Dist: h5py>=3.10.0
Requires-Dist: scipy>=1.14.0
Provides-Extra: optional
Requires-Dist: matplotlib>=3.9.0; extra == "optional"
Requires-Dist: scikit-learn>=1.5.0; extra == "optional"
